{
  "about-us": [
    {
      "lang": "en",
      "slug": "about-us"
    },
    {
      "lang": "nb",
      "slug": "om-oss"
    },
    {
      "lang": "es",
      "slug": "acerca-de-nosotros"
    },
    {
      "lang": "fr",
      "slug": "a-propos-de-nous"
    },
    {
      "lang": "fi",
      "slug": "meistä"
    },
    {
      "lang": "hu",
      "slug": "rolunk"
    },
    {
      "lang": "it",
      "slug": "chi-siamo"
    },
    {
      "lang": "pl",
      "slug": "o-nas"
    },
    {
      "lang": "pt-pt",
      "slug": "sobre-nos"
    },
    {
      "lang": "ro",
      "slug": "despre-noi"
    },
    {
      "lang": "ru",
      "slug": "o-nas"
    },
    {
      "lang": "sv",
      "slug": "om-oss"
    },
    {
      "lang": "de",
      "slug": "über-uns"
    },
    {
      "lang": "nl",
      "slug": "christelijke-gemeente-nederland"
    },
    {
      "lang": "da",
      "slug": "om-os"
    }
  ],
  "contributor": [
    {
      "lang": "en",
      "slug": "contributor"
    },
    {
      "lang": "nb",
      "slug": "bidragsyter"
    },
    {
      "lang": "es",
      "slug": "colaborador"
    },
    {
      "lang": "fr",
      "slug": "contributeur"
    },
    {
      "lang": "fi",
      "slug": "avustaja"
    },
    {
      "lang": "hu",
      "slug": "kozremukodo"
    },
    {
      "lang": "it",
      "slug": "autore"
    },
    {
      "lang": "pl",
      "slug": "współautor"
    },
    {
      "lang": "pt-pt",
      "slug": "contribuinte"
    },
    {
      "lang": "ro",
      "slug": "autor"
    },
    {
      "lang": "ru",
      "slug": "avtor"
    },
    {
      "lang": "sv",
      "slug": "bidragsgivare"
    },
    {
      "lang": "de",
      "slug": "mitwirkende"
    },
    {
      "lang": "nl",
      "slug": "auteur"
    },
    {
      "lang": "da",
      "slug": "bidragsyder"
    }
  ],
  "account": [
    {
      "lang": "en",
      "slug": "account"
    },
    {
      "lang": "nb",
      "slug": "konto"
    },
    {
      "lang": "es",
      "slug": "cuenta"
    },
    {
      "lang": "fr",
      "slug": "compte"
    },
    {
      "lang": "fi",
      "slug": ""
    },
    {
      "lang": "hu",
      "slug": "fiok"
    },
    {
      "lang": "it",
      "slug": "account"
    },
    {
      "lang": "pl",
      "slug": "konto"
    },
    {
      "lang": "pt-pt",
      "slug": "conta"
    },
    {
      "lang": "ro",
      "slug": "cont"
    },
    {
      "lang": "ru",
      "slug": "akkaunt"
    },
    {
      "lang": "sv",
      "slug": "konto"
    },
    {
      "lang": "de",
      "slug": ""
    },
    {
      "lang": "nl",
      "slug": "account"
    },
    {
      "lang": "da",
      "slug": "konto"
    }
  ],
  "contact": [
    {
      "lang": "en",
      "slug": "contact"
    },
    {
      "lang": "nb",
      "slug": "kontakt"
    },
    {
      "lang": "es",
      "slug": "contacto"
    },
    {
      "lang": "fr",
      "slug": "contact"
    },
    {
      "lang": "fi",
      "slug": ""
    },
    {
      "lang": "hu",
      "slug": "kapcsolat"
    },
    {
      "lang": "it",
      "slug": "contatto"
    },
    {
      "lang": "pl",
      "slug": "kontakt"
    },
    {
      "lang": "pt-pt",
      "slug": "contato"
    },
    {
      "lang": "ro",
      "slug": "contact"
    },
    {
      "lang": "ru",
      "slug": "kontakt"
    },
    {
      "lang": "sv",
      "slug": "kontakt"
    },
    {
      "lang": "de",
      "slug": ""
    },
    {
      "lang": "nl",
      "slug": "contact"
    },
    {
      "lang": "da",
      "slug": "kontakt"
    }
  ],
  "cookie-policy": [
    {
      "lang": "en",
      "slug": "cookie-policy"
    },
    {
      "lang": "nb",
      "slug": "cookie-policy"
    },
    {
      "lang": "es",
      "slug": "cookie-policy"
    },
    {
      "lang": "fr",
      "slug": "cookie-policy"
    },
    {
      "lang": "fi",
      "slug": "cookie-policy"
    },
    {
      "lang": "hu",
      "slug": "cookie-policy"
    },
    {
      "lang": "it",
      "slug": "cookie-policy"
    },
    {
      "lang": "pl",
      "slug": "Polityka Cookie"
    },
    {
      "lang": "pt-pt",
      "slug": "cookie-policy"
    },
    {
      "lang": "ro",
      "slug": "cookie-policy"
    },
    {
      "lang": "ru",
      "slug": "cookie-policy"
    },
    {
      "lang": "sv",
      "slug": "cookie-policy"
    },
    {
      "lang": "de",
      "slug": ""
    },
    {
      "lang": "nl",
      "slug": "cookie-policy"
    },
    {
      "lang": "da",
      "slug": "cookie-policy"
    }
  ],
  "e-book": [
    {
      "lang": "en",
      "slug": "e-book"
    },
    {
      "lang": "nb",
      "slug": "e-bok"
    },
    {
      "lang": "es",
      "slug": "e-book"
    },
    {
      "lang": "fr",
      "slug": "e-book"
    },
    {
      "lang": "fi",
      "slug": ""
    },
    {
      "lang": "hu",
      "slug": "e-konyv"
    },
    {
      "lang": "it",
      "slug": "e-book"
    },
    {
      "lang": "pl",
      "slug": "e-book"
    },
    {
      "lang": "pt-pt",
      "slug": "e-book"
    },
    {
      "lang": "ro",
      "slug": "e-book"
    },
    {
      "lang": "ru",
      "slug": "elkniga"
    },
    {
      "lang": "sv",
      "slug": "e-bok"
    },
    {
      "lang": "de",
      "slug": ""
    },
    {
      "lang": "nl",
      "slug": "e-book"
    },
    {
      "lang": "da",
      "slug": "e-bog"
    }
  ],
  "explore": [
    {
      "lang": "en",
      "slug": "explore"
    },
    {
      "lang": "nb",
      "slug": "utforsk"
    },
    {
      "lang": "es",
      "slug": "explorar"
    },
    {
      "lang": "fr",
      "slug": "explorer"
    },
    {
      "lang": "fi",
      "slug": ""
    },
    {
      "lang": "hu",
      "slug": "felfedezes"
    },
    {
      "lang": "it",
      "slug": "esplora"
    },
    {
      "lang": "pl",
      "slug": "odkryj"
    },
    {
      "lang": "pt-pt",
      "slug": "explorar"
    },
    {
      "lang": "ro",
      "slug": "exploreaza"
    },
    {
      "lang": "ru",
      "slug": "izuchi"
    },
    {
      "lang": "sv",
      "slug": "utforska"
    },
    {
      "lang": "de",
      "slug": ""
    },
    {
      "lang": "nl",
      "slug": "verken"
    },
    {
      "lang": "da",
      "slug": "udforsk"
    }
  ],
  "glossary": [
    {
      "lang": "en",
      "slug": "glossary"
    },
    {
      "lang": "nb",
      "slug": "ordliste"
    },
    {
      "lang": "es",
      "slug": "glosario"
    },
    {
      "lang": "fr",
      "slug": "glossaire"
    },
    {
      "lang": "fi",
      "slug": ""
    },
    {
      "lang": "hu",
      "slug": "szojegyzek"
    },
    {
      "lang": "it",
      "slug": "glossario"
    },
    {
      "lang": "pl",
      "slug": "słowniczek"
    },
    {
      "lang": "pt-pt",
      "slug": "dicionario"
    },
    {
      "lang": "ro",
      "slug": "glosar"
    },
    {
      "lang": "ru",
      "slug": "slovar"
    },
    {
      "lang": "sv",
      "slug": "ordlista"
    },
    {
      "lang": "de",
      "slug": ""
    },
    {
      "lang": "nl",
      "slug": "woordenlijst"
    },
    {
      "lang": "da",
      "slug": "Ordliste"
    }
  ],
  "host": [
    {
      "lang": "en",
      "slug": "host"
    },
    {
      "lang": "nb",
      "slug": "vert"
    },
    {
      "lang": "es",
      "slug": "anfitrion"
    },
    {
      "lang": "fr",
      "slug": "animateur "
    },
    {
      "lang": "fi",
      "slug": ""
    },
    {
      "lang": "hu",
      "slug": "musorvezeto"
    },
    {
      "lang": "it",
      "slug": "host"
    },
    {
      "lang": "pl",
      "slug": "gospodarz"
    },
    {
      "lang": "pt-pt",
      "slug": "hospedeiro"
    },
    {
      "lang": "ro",
      "slug": "host"
    },
    {
      "lang": "ru",
      "slug": "khozyain"
    },
    {
      "lang": "sv",
      "slug": "vard"
    },
    {
      "lang": "de",
      "slug": ""
    },
    {
      "lang": "nl",
      "slug": "host"
    },
    {
      "lang": "da",
      "slug": "vært"
    }
  ],
  "latest": [
    {
      "lang": "en",
      "slug": "latest"
    },
    {
      "lang": "nb",
      "slug": "nyeste"
    },
    {
      "lang": "es",
      "slug": "novedades"
    },
    {
      "lang": "fr",
      "slug": "le-plus-recent"
    },
    {
      "lang": "fi",
      "slug": ""
    },
    {
      "lang": "hu",
      "slug": "legujabb"
    },
    {
      "lang": "it",
      "slug": "ultimo"
    },
    {
      "lang": "pl",
      "slug": "najnowsze"
    },
    {
      "lang": "pt-pt",
      "slug": "ultimo"
    },
    {
      "lang": "ro",
      "slug": "ultimele"
    },
    {
      "lang": "ru",
      "slug": "novyye"
    },
    {
      "lang": "sv",
      "slug": "senaste"
    },
    {
      "lang": "de",
      "slug": ""
    },
    {
      "lang": "nl",
      "slug": "laatste"
    },
    {
      "lang": "da",
      "slug": "seneste"
    }
  ],
  "listen": [
    {
      "lang": "en",
      "slug": "listen"
    },
    {
      "lang": "nb",
      "slug": "lytt"
    },
    {
      "lang": "es",
      "slug": "escucha"
    },
    {
      "lang": "fr",
      "slug": "ecouter"
    },
    {
      "lang": "fi",
      "slug": ""
    },
    {
      "lang": "hu",
      "slug": "hallgatas"
    },
    {
      "lang": "it",
      "slug": "ascolta"
    },
    {
      "lang": "pl",
      "slug": "posłuchaj"
    },
    {
      "lang": "pt-pt",
      "slug": "ouca"
    },
    {
      "lang": "ro",
      "slug": "asculta"
    },
    {
      "lang": "ru",
      "slug": "proslushat"
    },
    {
      "lang": "sv",
      "slug": "lyssna"
    },
    {
      "lang": "de",
      "slug": ""
    },
    {
      "lang": "nl",
      "slug": "luister"
    },
    {
      "lang": "da",
      "slug": "lyt"
    }
  ],
  "login": [
    {
      "lang": "en",
      "slug": "login"
    },
    {
      "lang": "nb",
      "slug": "logg-pa"
    },
    {
      "lang": "es",
      "slug": "iniciar-sesion"
    },
    {
      "lang": "fr",
      "slug": "se-connecter"
    },
    {
      "lang": "fi",
      "slug": ""
    },
    {
      "lang": "hu",
      "slug": "bejelentkezes"
    },
    {
      "lang": "it",
      "slug": "login"
    },
    {
      "lang": "pl",
      "slug": "zaloguj"
    },
    {
      "lang": "pt-pt",
      "slug": "login"
    },
    {
      "lang": "ro",
      "slug": "logheaza-te"
    },
    {
      "lang": "ru",
      "slug": "voyti"
    },
    {
      "lang": "sv",
      "slug": "inloggning"
    },
    {
      "lang": "de",
      "slug": ""
    },
    {
      "lang": "nl",
      "slug": "login"
    },
    {
      "lang": "da",
      "slug": "log ind"
    }
  ],
  "playlist": [
    {
      "lang": "en",
      "slug": "playlist"
    },
    {
      "lang": "nb",
      "slug": "FALSE"
    },
    {
      "lang": "es",
      "slug": "FALSE"
    },
    {
      "lang": "fr",
      "slug": "FALSE"
    },
    {
      "lang": "fi",
      "slug": "FALSE"
    },
    {
      "lang": "hu",
      "slug": "FALSE"
    },
    {
      "lang": "it",
      "slug": "FALSE"
    },
    {
      "lang": "pl",
      "slug": "FALSE"
    },
    {
      "lang": "pt-pt",
      "slug": "FALSE"
    },
    {
      "lang": "ro",
      "slug": "FALSE"
    },
    {
      "lang": "ru",
      "slug": "FALSE"
    },
    {
      "lang": "sv",
      "slug": "FALSE"
    },
    {
      "lang": "de",
      "slug": "FALSE"
    },
    {
      "lang": "nl",
      "slug": "FALSE"
    },
    {
      "lang": "da",
      "slug": "FALSE"
    }
  ],
  "podcast": [
    {
      "lang": "en",
      "slug": "podcast"
    },
    {
      "lang": "nb",
      "slug": "FALSE"
    },
    {
      "lang": "es",
      "slug": "FALSE"
    },
    {
      "lang": "fr",
      "slug": "FALSE"
    },
    {
      "lang": "fi",
      "slug": "FALSE"
    },
    {
      "lang": "hu",
      "slug": "FALSE"
    },
    {
      "lang": "it",
      "slug": "FALSE"
    },
    {
      "lang": "pl",
      "slug": "FALSE"
    },
    {
      "lang": "pt-pt",
      "slug": "FALSE"
    },
    {
      "lang": "ro",
      "slug": "FALSE"
    },
    {
      "lang": "ru",
      "slug": "FALSE"
    },
    {
      "lang": "sv",
      "slug": "FALSE"
    },
    {
      "lang": "de",
      "slug": "FALSE"
    },
    {
      "lang": "nl",
      "slug": "FALSE"
    },
    {
      "lang": "da",
      "slug": "FALSE"
    }
  ],
  "living-the-gospel-intro": [
    {
      "lang": "en",
      "slug": "living-the-gospel-intro"
    },
    {
      "lang": "nb",
      "slug": "living-the-gospel-intro"
    },
    {
      "lang": "es",
      "slug": "living-the-gospel-intro"
    },
    {
      "lang": "fr",
      "slug": "living-the-gospel-intro"
    },
    {
      "lang": "fi",
      "slug": ""
    },
    {
      "lang": "hu",
      "slug": "elni-az-evangeliumot-intro"
    },
    {
      "lang": "it",
      "slug": "vivere-il-vangelo-intro"
    },
    {
      "lang": "pl",
      "slug": "zycie-wg-ewangelii-wstep"
    },
    {
      "lang": "pt-pt",
      "slug": "Introducao-vivendo-o-evangelho"
    },
    {
      "lang": "ro",
      "slug": "living-the-gospel-intro"
    },
    {
      "lang": "ru",
      "slug": "zhizn-s-yevangeliyem-vstupleniye"
    },
    {
      "lang": "sv",
      "slug": "living-the-gospel-intro"
    },
    {
      "lang": "de",
      "slug": ""
    },
    {
      "lang": "nl",
      "slug": "leef-het-evangelie-intro"
    },
    {
      "lang": "da",
      "slug": "living-the-gospel-intro"
    }
  ],
  "privacy-policy": [
    {
      "lang": "en",
      "slug": "privacy-policy"
    },
    {
      "lang": "nb",
      "slug": "privacy-policy"
    },
    {
      "lang": "es",
      "slug": "privacy-policy"
    },
    {
      "lang": "fr",
      "slug": "privacy-policy"
    },
    {
      "lang": "fi",
      "slug": "privacy-policy"
    },
    {
      "lang": "hu",
      "slug": "privacy-policy"
    },
    {
      "lang": "it",
      "slug": "privacy-policy"
    },
    {
      "lang": "pl",
      "slug": "Polityka prywatności"
    },
    {
      "lang": "pt-pt",
      "slug": "privacy-policy"
    },
    {
      "lang": "ro",
      "slug": "privacy-policy"
    },
    {
      "lang": "ru",
      "slug": "privacy-policy"
    },
    {
      "lang": "sv",
      "slug": "privacy-policy"
    },
    {
      "lang": "de",
      "slug": "privacy-policy"
    },
    {
      "lang": "nl",
      "slug": "privacy-policy"
    },
    {
      "lang": "da",
      "slug": "privacy-policy"
    }
  ],
  "read": [
    {
      "lang": "en",
      "slug": "read"
    },
    {
      "lang": "nb",
      "slug": "les"
    },
    {
      "lang": "es",
      "slug": "leer"
    },
    {
      "lang": "fr",
      "slug": "lire"
    },
    {
      "lang": "fi",
      "slug": ""
    },
    {
      "lang": "hu",
      "slug": "cikkek"
    },
    {
      "lang": "it",
      "slug": "leggi"
    },
    {
      "lang": "pl",
      "slug": "przeczytaj"
    },
    {
      "lang": "pt-pt",
      "slug": "ler"
    },
    {
      "lang": "ro",
      "slug": "citeste"
    },
    {
      "lang": "ru",
      "slug": "prochitat"
    },
    {
      "lang": "sv",
      "slug": "las"
    },
    {
      "lang": "de",
      "slug": ""
    },
    {
      "lang": "nl",
      "slug": "lees"
    },
    {
      "lang": "da",
      "slug": "læs"
    }
  ],
  "register": [
    {
      "lang": "en",
      "slug": "register"
    },
    {
      "lang": "nb",
      "slug": "register"
    },
    {
      "lang": "es",
      "slug": "registrarse"
    },
    {
      "lang": "fr",
      "slug": "sincrire "
    },
    {
      "lang": "fi",
      "slug": ""
    },
    {
      "lang": "hu",
      "slug": "regisztracio"
    },
    {
      "lang": "it",
      "slug": "registra"
    },
    {
      "lang": "pl",
      "slug": "zarejestruj"
    },
    {
      "lang": "pt-pt",
      "slug": "registrar-se"
    },
    {
      "lang": "ro",
      "slug": "inregistreaza-te"
    },
    {
      "lang": "ru",
      "slug": "zaregistrirovat'sya"
    },
    {
      "lang": "sv",
      "slug": "registrera dig"
    },
    {
      "lang": "de",
      "slug": ""
    },
    {
      "lang": "nl",
      "slug": "Registreer"
    },
    {
      "lang": "da",
      "slug": "opret dig"
    }
  ],
  "scripture": [
    {
      "lang": "en",
      "slug": "scripture"
    },
    {
      "lang": "nb",
      "slug": "FALSE"
    },
    {
      "lang": "es",
      "slug": "FALSE"
    },
    {
      "lang": "fr",
      "slug": "FALSE"
    },
    {
      "lang": "fi",
      "slug": "FALSE"
    },
    {
      "lang": "hu",
      "slug": "FALSE"
    },
    {
      "lang": "it",
      "slug": "FALSE"
    },
    {
      "lang": "pl",
      "slug": "FALSE"
    },
    {
      "lang": "pt-pt",
      "slug": "FALSE"
    },
    {
      "lang": "ro",
      "slug": "FALSE"
    },
    {
      "lang": "ru",
      "slug": "FALSE"
    },
    {
      "lang": "sv",
      "slug": "FALSE"
    },
    {
      "lang": "de",
      "slug": "FALSE"
    },
    {
      "lang": "nl",
      "slug": "FALSE"
    },
    {
      "lang": "da",
      "slug": "FALSE"
    }
  ],
  "theme": [
    {
      "lang": "en",
      "slug": "theme"
    },
    {
      "lang": "nb",
      "slug": "tema"
    },
    {
      "lang": "es",
      "slug": "tema"
    },
    {
      "lang": "fr",
      "slug": "theme"
    },
    {
      "lang": "fi",
      "slug": ""
    },
    {
      "lang": "hu",
      "slug": "tema"
    },
    {
      "lang": "it",
      "slug": "tema"
    },
    {
      "lang": "pl",
      "slug": "zagadnienie"
    },
    {
      "lang": "pt-pt",
      "slug": "tema"
    },
    {
      "lang": "ro",
      "slug": "teme"
    },
    {
      "lang": "ru",
      "slug": "tema"
    },
    {
      "lang": "sv",
      "slug": "tema"
    },
    {
      "lang": "de",
      "slug": ""
    },
    {
      "lang": "nl",
      "slug": "thema"
    },
    {
      "lang": "da",
      "slug": "tema"
    }
  ],
  "topic": [
    {
      "lang": "en",
      "slug": "topic"
    },
    {
      "lang": "nb",
      "slug": "tema"
    },
    {
      "lang": "es",
      "slug": "tema"
    },
    {
      "lang": "fr",
      "slug": "theme"
    },
    {
      "lang": "fi",
      "slug": "teemat"
    },
    {
      "lang": "hu",
      "slug": "temak"
    },
    {
      "lang": "it",
      "slug": "argomento"
    },
    {
      "lang": "pl",
      "slug": "temat"
    },
    {
      "lang": "pt-pt",
      "slug": "topicos"
    },
    {
      "lang": "ro",
      "slug": "topica"
    },
    {
      "lang": "ru",
      "slug": "tema"
    },
    {
      "lang": "sv",
      "slug": "tema"
    },
    {
      "lang": "de",
      "slug": "thema"
    },
    {
      "lang": "nl",
      "slug": "onderwerpen"
    },
    {
      "lang": "da",
      "slug": "temaer"
    }
  ],
  "user": [
    {
      "lang": "en",
      "slug": "user"
    },
    {
      "lang": "nb",
      "slug": "user"
    },
    {
      "lang": "es",
      "slug": "usuario"
    },
    {
      "lang": "fr",
      "slug": "utilisateur"
    },
    {
      "lang": "fi",
      "slug": ""
    },
    {
      "lang": "hu",
      "slug": "felhasznalo"
    },
    {
      "lang": "it",
      "slug": "utente"
    },
    {
      "lang": "pl",
      "slug": "uzytkownik"
    },
    {
      "lang": "pt-pt",
      "slug": "usuario"
    },
    {
      "lang": "ro",
      "slug": "utilizator"
    },
    {
      "lang": "ru",
      "slug": "polzovatel"
    },
    {
      "lang": "sv",
      "slug": "anvandare"
    },
    {
      "lang": "de",
      "slug": ""
    },
    {
      "lang": "nl",
      "slug": "gebruiker"
    },
    {
      "lang": "da",
      "slug": "bruger"
    }
  ],
  "bookmarked": [
    {
      "lang": "en",
      "slug": "bookmarked"
    },
    {
      "lang": "nb",
      "slug": "merket"
    },
    {
      "lang": "es",
      "slug": "guardado"
    },
    {
      "lang": "fr",
      "slug": "ajoute-en-favoris"
    },
    {
      "lang": "fi",
      "slug": ""
    },
    {
      "lang": "hu",
      "slug": "konyvjelzo-mentve"
    },
    {
      "lang": "it",
      "slug": "preferiti"
    },
    {
      "lang": "pl",
      "slug": "dodano-do-zakładek"
    },
    {
      "lang": "pt-pt",
      "slug": "selecionado"
    },
    {
      "lang": "ro",
      "slug": "marcat"
    },
    {
      "lang": "ru",
      "slug": "dobvleno-v-zakladki"
    },
    {
      "lang": "sv",
      "slug": "bokmarkt"
    },
    {
      "lang": "de",
      "slug": ""
    },
    {
      "lang": "nl",
      "slug": "bewaard"
    },
    {
      "lang": "da",
      "slug": "bogmærket"
    }
  ],
  "password": [
    {
      "lang": "en",
      "slug": "password"
    },
    {
      "lang": "nb",
      "slug": "endre-passord"
    },
    {
      "lang": "es",
      "slug": "contraseña"
    },
    {
      "lang": "fr",
      "slug": "mot-de-passe"
    },
    {
      "lang": "fi",
      "slug": ""
    },
    {
      "lang": "hu",
      "slug": "jelszo"
    },
    {
      "lang": "it",
      "slug": "password"
    },
    {
      "lang": "pl",
      "slug": "hasło"
    },
    {
      "lang": "pt-pt",
      "slug": "senha"
    },
    {
      "lang": "ro",
      "slug": "parola"
    },
    {
      "lang": "ru",
      "slug": "parol"
    },
    {
      "lang": "sv",
      "slug": "losenord"
    },
    {
      "lang": "de",
      "slug": ""
    },
    {
      "lang": "nl",
      "slug": "wachtwoord"
    },
    {
      "lang": "da",
      "slug": "password"
    }
  ],
  "my-content": [
    {
      "lang": "en",
      "slug": "my-content"
    },
    {
      "lang": "nb",
      "slug": "mitt-innhold"
    },
    {
      "lang": "es",
      "slug": "mi-contenido "
    },
    {
      "lang": "fr",
      "slug": "mon-contenu"
    },
    {
      "lang": "fi",
      "slug": ""
    },
    {
      "lang": "hu",
      "slug": "sajat-tartalom"
    },
    {
      "lang": "it",
      "slug": "il-mio-contenuto"
    },
    {
      "lang": "pl",
      "slug": "moje-tresci"
    },
    {
      "lang": "pt-pt",
      "slug": "minha-conta"
    },
    {
      "lang": "ro",
      "slug": "continutul-meu"
    },
    {
      "lang": "ru",
      "slug": "moyo-soderzhaniye"
    },
    {
      "lang": "sv",
      "slug": "mitt-innehall"
    },
    {
      "lang": "de",
      "slug": ""
    },
    {
      "lang": "nl",
      "slug": "mijn-inhoud"
    },
    {
      "lang": "da",
      "slug": "mit-indhold"
    }
  ],
  "delete-profile": [
    {
      "lang": "en",
      "slug": "delete-profile"
    },
    {
      "lang": "nb",
      "slug": "slett-profil"
    },
    {
      "lang": "es",
      "slug": "borrar-cuenta"
    },
    {
      "lang": "fr",
      "slug": "Supprimer-mon-profil"
    },
    {
      "lang": "fi",
      "slug": ""
    },
    {
      "lang": "hu",
      "slug": "profil-torlese"
    },
    {
      "lang": "it",
      "slug": "elimina-profilo"
    },
    {
      "lang": "pl",
      "slug": "usun-profil"
    },
    {
      "lang": "pt-pt",
      "slug": "deletar-perfil"
    },
    {
      "lang": "ro",
      "slug": "sterge-profil"
    },
    {
      "lang": "ru",
      "slug": "udalit-profil"
    },
    {
      "lang": "sv",
      "slug": "radera-profil"
    },
    {
      "lang": "de",
      "slug": ""
    },
    {
      "lang": "nl",
      "slug": "verwijder-profiel"
    },
    {
      "lang": "da",
      "slug": "slet-profil"
    }
  ],
  "followed": [
    {
      "lang": "en",
      "slug": "followed"
    },
    {
      "lang": "nb",
      "slug": "folger"
    },
    {
      "lang": "es",
      "slug": "seguido"
    },
    {
      "lang": "fr",
      "slug": "suivis"
    },
    {
      "lang": "fi",
      "slug": ""
    },
    {
      "lang": "hu",
      "slug": "kovetem"
    },
    {
      "lang": "it",
      "slug": "seguito"
    },
    {
      "lang": "pl",
      "slug": "obserwowane"
    },
    {
      "lang": "pt-pt",
      "slug": "seguindo"
    },
    {
      "lang": "ro",
      "slug": "urmarit"
    },
    {
      "lang": "ru",
      "slug": "podpisan"
    },
    {
      "lang": "sv",
      "slug": "foljer"
    },
    {
      "lang": "de",
      "slug": ""
    },
    {
      "lang": "nl",
      "slug": "gevolgd"
    },
    {
      "lang": "da",
      "slug": "følger"
    }
  ],
  "history": [
    {
      "lang": "en",
      "slug": "history"
    },
    {
      "lang": "nb",
      "slug": "historikk"
    },
    {
      "lang": "es",
      "slug": "historial"
    },
    {
      "lang": "fr",
      "slug": "historique"
    },
    {
      "lang": "fi",
      "slug": ""
    },
    {
      "lang": "hu",
      "slug": "elozmenyek"
    },
    {
      "lang": "it",
      "slug": "storia"
    },
    {
      "lang": "pl",
      "slug": "historia"
    },
    {
      "lang": "pt-pt",
      "slug": "historia"
    },
    {
      "lang": "ro",
      "slug": "istorie"
    },
    {
      "lang": "ru",
      "slug": "istoriya"
    },
    {
      "lang": "sv",
      "slug": "historik"
    },
    {
      "lang": "de",
      "slug": ""
    },
    {
      "lang": "nl",
      "slug": "geschiedenis"
    },
    {
      "lang": "da",
      "slug": "historik"
    }
  ],
  "watch": [
    {
      "lang": "en",
      "slug": "watch"
    },
    {
      "lang": "nb",
      "slug": "se-paa"
    },
    {
      "lang": "es",
      "slug": "ver"
    },
    {
      "lang": "fr",
      "slug": "visionner"
    },
    {
      "lang": "fi",
      "slug": ""
    },
    {
      "lang": "hu",
      "slug": "videok"
    },
    {
      "lang": "it",
      "slug": "guarda"
    },
    {
      "lang": "pl",
      "slug": "obejrzyj"
    },
    {
      "lang": "pt-pt",
      "slug": "veja"
    },
    {
      "lang": "ro",
      "slug": "vizioneaza"
    },
    {
      "lang": "ru",
      "slug": "posmotri"
    },
    {
      "lang": "sv",
      "slug": "se"
    },
    {
      "lang": "de",
      "slug": ""
    },
    {
      "lang": "nl",
      "slug": "bekijk"
    },
    {
      "lang": "da",
      "slug": "se"
    }
  ]
}